gitver/__init__.py
gitver/gitver.py
whoi_gitver-0.0.3.dist-info/LICENSE
whoi_gitver-0.0.3.dist-info/METADATA
whoi_gitver-0.0.3.dist-info/WHEEL
whoi_gitver-0.0.3.dist-info/top_level.txt
whoi_gitver-0.0.3.dist-info/RECORD
