Metadata-Version: 2.1
Name: whoi-gitver
Version: 0.0.3
Summary: whoi_gitver
Home-page: https://git.whoi.edu/acomms/gitver
Author: whoi
Author-email: bmillerklugman@whoi.edu
License: UNKNOWN
Project-URL: Bug Tracker, https://git.whoi.edu/acomms/gitver
Platform: UNKNOWN
Classifier: Programming Language :: Python :: 3
Classifier: License :: OSI Approved :: GNU Lesser General Public License v3 or later (LGPLv3+)
Classifier: Operating System :: OS Independent
Requires-Python: >=3.6
License-File: LICENSE
